aiohttp_serve/__init__.py
aiohttp_serve/_config.py
aiohttp_serve/_logging.py
aiohttp_serve/_main.py
aiohttp_serve/_socket.py
aiohttp_serve/_supervisor.py
aiohttp_serve/_utils.py
aiohttp_serve/_worker.py
aiohttp_serve-0.2.2.dist-info/LICENSE.txt
aiohttp_serve-0.2.2.dist-info/METADATA
aiohttp_serve-0.2.2.dist-info/WHEEL
aiohttp_serve-0.2.2.dist-info/top_level.txt
aiohttp_serve-0.2.2.dist-info/RECORD
