Metadata-Version: 2.1
Name: aiohttp-serve
Version: 0.2.2
Summary: Multiprocessing based aiohttp application runner
Home-page: https://github.com/romis2012/aiohttp-serve
Author: Roman Snegirev
Author-email: snegiryev@gmail.com
License: Apache 2
Keywords: asyncio aiohttp multiprocessing supervisor
Platform: UNKNOWN
License-File: LICENSE.txt
Requires-Dist: aiohttp (>=3.7.4)
